tamil_tokenizer/__init__.py
tamil_tokenizer/cli.py
tamil_tokenizer/core.py
tamil_tokenizer/exceptions.py
tamil_tokenizer-0.1.1.dist-info/licenses/LICENSE
tamil_tokenizer-0.1.1.dist-info/METADATA
tamil_tokenizer-0.1.1.dist-info/WHEEL
tamil_tokenizer-0.1.1.dist-info/entry_points.txt
tamil_tokenizer-0.1.1.dist-info/top_level.txt
tamil_tokenizer-0.1.1.dist-info/RECORD
