Metadata-Version: 2.4
Name: tamil-tokenizer
Version: 0.1.1
Summary: A simple Tamil text tokenizer library with modern Python structure
Author-email: Raja CSP Raman <raja.csp@gmail.com>
License: Apache-2.0
Project-URL: Homepage, https://github.com/rajacsp/tamil-tokenizer
Project-URL: Repository, https://github.com/rajacsp/tamil-tokenizer
Project-URL: Issues, https://github.com/rajacsp/tamil-tokenizer/issues
Keywords: tamil,tokenizer,nlp,text-processing,language
Classifier: Development Status :: 4 - Beta
Classifier: Intended Audience :: Developers
Classifier: License :: OSI Approved :: Apache Software License
Classifier: Operating System :: OS Independent
Classifier: Programming Language :: Python :: 3
Classifier: Programming Language :: Python :: 3.8
Classifier: Programming Language :: Python :: 3.9
Classifier: Programming Language :: Python :: 3.10
Classifier: Programming Language :: Python :: 3.11
Classifier: Programming Language :: Python :: 3.12
Classifier: Topic :: Software Development :: Libraries :: Python Modules
Classifier: Topic :: Text Processing :: Linguistic
Classifier: Topic :: Scientific/Engineering :: Artificial Intelligence
Requires-Python: >=3.8
License-File: LICENSE
Requires-Dist: regex>=2022.0.0
Provides-Extra: dev
Requires-Dist: pytest>=7.0.0; extra == "dev"
Requires-Dist: pytest-cov>=4.0.0; extra == "dev"
Requires-Dist: black>=22.0.0; extra == "dev"
Requires-Dist: flake8>=5.0.0; extra == "dev"
Requires-Dist: mypy>=1.0.0; extra == "dev"
Dynamic: license-file
